{
	"tab1" : {
		"name" : "烟酒 / 粮油 / 乳制品",
		"list" : [
			{
				"id" : "烟草",
				"name" : "卷烟"
			},
			{
				"id" : "美酒佳肴",
				"name" : "白酒 | 黄酒 | 葡萄酒 | 啤酒 | 洋酒 | 补酒"
			},
			{
				"id" : "米面杂粮",
				"name" : "米 | 面/面制品 | 杂粮"
			},
			{
				"id" : "乳制品",
				"name" : "常温鲜奶 | 常温酸奶 | 豆奶 | 其他乳制品"
			},
			{
				"id" : "食用油",
				"name" : "调和油 | 橄榄油 | 玉米油 | 大豆油"
			},
			{
				"id" : "乳制品",
				"name" : "常温鲜奶 | 常温酸奶 | 豆奶 | 其他乳制品"
			},
			{
				"id" : "食用油",
				"name" : "调和油 | 橄榄油 | 玉米油 | 大豆油"
			},
			{
				"id" : "奶制品",
				"name" : "高钙奶粉 | 中老年奶粉 | 全脂奶粉 | 豆奶粉"
			}

		]
	},
	"tab2" : {
		"name" : "生鲜 / 干货 / 调料",
		"list" : [
			{
				"id" : "蛋肉家禽",
				"name" : "蛋类 | 猪肉类 | 牛羊肉 | 禽类 | 腌腊制品"
			},
			{
				"id" : "时鲜蔬果",
				"name" : "豆制品"
			},
			{
				"id" : "蛋肉家禽",
				"name" : "蛋类 | 猪肉类 | 牛羊肉 | 禽类 | 腌腊制品"
			},
			{
				"id" : "海鲜水产",
				"name" : "鱼类 | 虾类 | 其他海产品"
			},
			{
				"id" : "蛋肉家禽",
				"name" : "蛋类 | 猪肉类 | 牛羊肉 | 禽类 | 腌腊制品"
			},
			{
				"id" : "南北干货",
				"name" : "菌菇类 | 红枣类 | 桂圆类 | 木耳类 | 枸杞类"
			},
			{
				"id" : "厨房调料",
				"name" : "酱油 | 糖 | 盐 | 醋 | 麻油"
			},
			{
				"id" : "半成品/熟食",
				"name" : "现制点心 | 冷冻米面制品 | 冷冻肉类制品"
			}
		]
	},
	"tab3" : {
		"name" : "食品 / 饮料",
		"list" : [
			{
				"id" : "烟草",
				"name" : "卷烟"
			},
			{
				"id" : "美酒佳肴",
				"name" : "白酒 | 黄酒 | 葡萄酒 | 啤酒 | 洋酒 | 补酒"
			},
			{
				"id" : "米面杂粮",
				"name" : "米 | 面/面制品 | 杂粮"
			},
			{
				"id" : "美酒佳肴",
				"name" : "白酒 | 黄酒 | 葡萄酒 | 啤酒 | 洋酒 | 补酒"
			},
			{
				"id" : "乳制品",
				"name" : "常温鲜奶 | 常温酸奶 | 豆奶 | 其他乳制品"
			},
			{
				"id" : "美酒佳肴",
				"name" : "白酒 | 黄酒 | 葡萄酒 | 啤酒 | 洋酒 | 补酒"
			},
			{
				"id" : "食用油",
				"name" : "调和油 | 橄榄油 | 玉米油 | 大豆油"
			},
			{
				"id" : "奶制品",
				"name" : "高钙奶粉 | 中老年奶粉 | 全脂奶粉 | 豆奶粉"
			}
		]	
		},
	"tab4" : {
		"name" : "母婴服饰 / 床上用品",
		"list" : [
			{
				"id" : "蛋肉家禽",
				"name" : "蛋类 | 猪肉类 | 牛羊肉 | 禽类 | 腌腊制品"
			},
			{
				"id" : "时鲜蔬果",
				"name" : "豆制品"
			},
			{
				"id" : "蛋肉家禽",
				"name" : "蛋类 | 猪肉类 | 牛羊肉 | 禽类 | 腌腊制品"
			},
			{
				"id" : "海鲜水产",
				"name" : "鱼类 | 虾类 | 其他海产品"
			},
			{
				"id" : "南北干货",
				"name" : "菌菇类 | 红枣类 | 桂圆类 | 木耳类 | 枸杞类"
			},
			{
				"id" : "蛋肉家禽",
				"name" : "蛋类 | 猪肉类 | 牛羊肉 | 禽类 | 腌腊制品"
			},
			{
				"id" : "厨房调料",
				"name" : "酱油 | 糖 | 盐 | 醋 | 麻油"
			},
			{
				"id" : "半成品/熟食",
				"name" : "现制点心 | 冷冻米面制品 | 冷冻肉类制品"
			}
		]
	},
	"tab5" : {
		"name" : "家电手机 / 生活电器",
		"list" : [
			{
				"id" : "烟草",
				"name" : "卷烟"
			},
			{
				"id" : "美酒佳肴",
				"name" : "白酒 | 黄酒 | 葡萄酒 | 啤酒 | 洋酒 | 补酒"
			},
			{
				"id" : "米面杂粮",
				"name" : "米 | 面/面制品 | 杂粮"
			},
			{
				"id" : "乳制品",
				"name" : "常温鲜奶 | 常温酸奶 | 豆奶 | 其他乳制品"
			},
			{
				"id" : "美酒佳肴",
				"name" : "白酒 | 黄酒 | 葡萄酒 | 啤酒 | 洋酒 | 补酒"
			},
			{
				"id" : "食用油",
				"name" : "调和油 | 橄榄油 | 玉米油 | 大豆油"
			},
			{
				"id" : "美酒佳肴",
				"name" : "白酒 | 黄酒 | 葡萄酒 | 啤酒 | 洋酒 | 补酒"
			},
			{
				"id" : "奶制品",
				"name" : "高钙奶粉 | 中老年奶粉 | 全脂奶粉 | 豆奶粉"
			}
		]
	},
	"tab6" : {
		"name" : "厨房用品 / 清洁用品",
		"list" : [
			{
				"id" : "蛋肉家禽",
				"name" : "蛋类 | 猪肉类 | 牛羊肉 | 禽类 | 腌腊制品"
			},
			{
				"id" : "时鲜蔬果",
				"name" : "豆制品"
			},
			{
				"id" : "海鲜水产",
				"name" : "鱼类 | 虾类 | 其他海产品"
			},
			{
				"id" : "蛋肉家禽",
				"name" : "蛋类 | 猪肉类 | 牛羊肉 | 禽类 | 腌腊制品"
			},
			{
				"id" : "南北干货",
				"name" : "菌菇类 | 红枣类 | 桂圆类 | 木耳类 | 枸杞类"
			},
			{
				"id" : "厨房调料",
				"name" : "酱油 | 糖 | 盐 | 醋 | 麻油"
			},
			{
				"id" : "蛋肉家禽",
				"name" : "蛋类 | 猪肉类 | 牛羊肉 | 禽类 | 腌腊制品"
			},
			{
				"id" : "半成品/熟食",
				"name" : "现制点心 | 冷冻米面制品 | 冷冻肉类制品"
			}
		]
	},
	"tab7" : {
		"name" : "个人护理 / 美容美发",
		"list" : [
			{
				"id" : "烟草",
				"name" : "卷烟"
			},
			{
				"id" : "蛋肉家禽",
				"name" : "蛋类 | 猪肉类 | 牛羊肉 | 禽类 | 腌腊制品"
			},
			{
				"id" : "米面杂粮",
				"name" : "米 | 面/面制品 | 杂粮"
			},
			{
				"id" : "蛋肉家禽",
				"name" : "蛋类 | 猪肉类 | 牛羊肉 | 禽类 | 腌腊制品"
			},
			{
				"id" : "乳制品",
				"name" : "常温鲜奶 | 常温酸奶 | 豆奶 | 其他乳制品"
			},
			{
				"id" : "食用油",
				"name" : "调和油 | 橄榄油 | 玉米油 | 大豆油"
			},
			{
				"id" : "蛋肉家禽",
				"name" : "蛋类 | 猪肉类 | 牛羊肉 | 禽类 | 腌腊制品"
			},
			{
				"id" : "奶制品",
				"name" : "高钙奶粉 | 中老年奶粉 | 全脂奶粉 | 豆奶粉"
			}
		]
	},
	"tab8" : {
		"name" : "礼品卡 / 其他商品",
		"list" : [
			{
				"id" : "蛋肉家禽",
				"name" : "蛋类 | 猪肉类 | 牛羊肉 | 禽类 | 腌腊制品"
			},
			{
				"id" : "时鲜蔬果",
				"name" : "豆制品"
			},
			{
				"id" : "蛋肉家禽",
				"name" : "蛋类 | 猪肉类 | 牛羊肉 | 禽类 | 腌腊制品"
			},
			{
				"id" : "海鲜水产",
				"name" : "鱼类 | 虾类 | 其他海产品"
			},
			{
				"id" : "南北干货",
				"name" : "菌菇类 | 红枣类 | 桂圆类 | 木耳类 | 枸杞类"
			},
			{
				"id" : "蛋肉家禽",
				"name" : "蛋类 | 猪肉类 | 牛羊肉 | 禽类 | 腌腊制品"
			},
			{
				"id" : "厨房调料",
				"name" : "酱油 | 糖 | 盐 | 醋 | 麻油"
			},
			{
				"id" : "半成品/熟食",
				"name" : "现制点心 | 冷冻米面制品 | 冷冻肉类制品"
			}
		]
	}
}